{
  "@context": "http://iiif.io/api/presentation/4/context.json",
  "id": "https://example.org/iiif/3d/model_origin.json",
  "type": "Manifest",
  "label": { "en": ["Model with Explicit Perspective Camera Looking at a Point"] },
  "summary": { "en": ["Viewer should render the model at the scene origin with a perspective camera looking toward the PointSelector coordinates, and add default lighting"] },
  "items": [
    {
      "id": "https://example.org/iiif/scene1/page/p1/1",
      "type": "Scene",
      "label": { "en": ["Scene with a Model and Camera Looking at a Point"] },

      "items": [
        {
          "id": "https://example.org/iiif/scene1/page/p1/1",
          "type": "AnnotationPage",
          "items": [
            {
              "id": "https://example.org/iiif/3d/anno1",
              "type": "Annotation",
              "motivation": ["painting"],
              "body": {
                "id": "https://github.com/IIIF/3d/raw/main/assets/astronaut/astronaut.glb",
                "type": "Model"
              },
              "target": "https://example.org/iiif/scene1/page/p1/1"
            },
            {
              "id": "https://example.org/iiif/3d/anno2",
              "type": "Annotation",
              "motivation": ["painting"],
              "body": {
                "id": "https://example.org/iiif/3d/cameras/1",
                "type": "PerspectiveCamera",
                "label": {"en": ["Perspective Camera 1"]},
                "lookAt": {
                  "type": "PointSelector",
                  "x": 2,
                  "y": 1,
                  "z": 0
                }
              },
              "target": {
                "type": "SpecificResource",
                "source": [
                  {
                    "id": "https://example.org/iiif/scene1/page/p1/1",
                    "type": "Scene"
                  }
                ],
                "selector": [
                  {
                    "type": "PointSelector",
                    "x": 0.0,
                    "y": 3.0,
                    "z": -10.0
                  }
                ]
              }
            }
          ]
        }
      ]
    }
  ]
}
